Metadata-Version: 2.1
Name: getsimilar
Version: 0.0.1
Summary: Image search: image/text => images.
Home-page: https://github.com/ternaus/getsimilar
Author: Vladimir Iglovikov
License: MIT
Classifier: Intended Audience :: Developers
Classifier: Intended Audience :: Science/Research
Classifier: Operating System :: OS Independent
Classifier: Programming Language :: Python
Classifier: Programming Language :: Python :: 3
Classifier: Topic :: Software Development :: Libraries
Classifier: Topic :: Software Development :: Libraries :: Python Modules
Provides-Extra: test
License-File: LICENSE
